hardware/common/frequencyDivider.v

module frequencyDivider#(parameter divider=10, parameter bitsNumber=4)(
	input   wire inputCLK,
    input   wire reset,
	output  reg  outputCLK
	);
    reg [bitsNumber-1:0] count;
    
    //Inicializacion
    initial begin count=0; outputCLK=0; end

    //Logica Secuencial
    always@(posedge inputCLK , posedge reset) begin
        if (reset == 1'b1) begin
            count <= 0;
            outputCLK <= 0;
        end else if (count == divider/2 -1) begin
            count <= count+1;
            outputCLK <= 1;
        end else if(count == divider-1) begin
            count <= 0;
            outputCLK <= 0;
        end else begin
            count <= count+1;  
        end  
    end
    
endmodule

Hardware/common/frequencyDivider_TB.v
// ============================================================================
// TESTBENCH FOR frequencyDivider
// ============================================================================
`timescale 1ns / 100ps
module SD_SPI_TB ();
    reg clk;
    reg reset;


    frequencyDivider #(.divider(2),.bitsNumber(2)) uut(
	    .inputCLK(clk),
        .reset(reset)
	);


    initial begin
        clk=0;
        reset=0;
        #50
        reset=1;
        #1
        reset=0;
    end

    always clk = #0.5 ~clk;

    initial begin: TEST_CASE
        $dumpfile("verilogTestBench.vcd");
        $dumpvars(-1, uut);
        #80000 $finish;
    end

endmodule

verilogTestBench.vcd
$date
	Sun Apr  4 18:47:47 2021
$end
$version
	Icarus Verilog
$end
$timescale
	100ps
$end
$scope module SD_SPI_TB $end
$scope module uut $end
$var wire 1 ! inputCLK $end
$var wire 1 " reset $end
$var reg 2 # count [1:0] $end
$var reg 1 $ outputCLK $end
$upscope $end
$upscope $end
$enddefinitions $end
#0
$dumpvars
0$
b0 #
0"
0!
$end
#5
1$
b1 #
1!
#10
0!
#15
0$
b0 #
1!
#20
0!
#25
1$
b1 #
1!
#30
0!
#35
0$
b0 #
1!
#40
0!
#45
1$
b1 #
1!
#50
0!
#55
0$
b0 #
1!
#60
0!
#65
1$
b1 #
1!
#70
0!
#75
0$
b0 #
1!
#80
0!
#85
1$
b1 #
1!
#90
0!
#95
0$
b0 #
1!
#100
0!
#105
1$
b1 #
1!
#110
0!
#115
0$
b0 #
1!
#120
0!
#125
1$
b1 #
1!
#130
0!
#135
0$
b0 #
1!
#140
0!
#145
1$
b1 #
1!
#150
0!
#155
0$
b0 #
1!
#160
0!
#165
1$
b1 #
1!
#170
0!
#175
0$
b0 #
1!
#180
0!
#185
1$
b1 #
1!
#190
0!
#195
0$
b0 #
1!
#200
0!
#205
1$
b1 #
1!
#210
0!
#215
0$
b0 #
1!
#220
0!
#225
1$
b1 #
1!
#230
0!
#235
0$
b0 #
1!
#240
0!
#245
1$
b1 #
1!
#250
0!
#255
0$
b0 #
1!
#260
0!
#265
1$
b1 #
1!
#270
0!
#275
0$
b0 #
1!
#280
0!
#285
1$
b1 #
1!
#290
0!
#295
0$
b0 #
1!
#300
0!
#305
1$
b1 #
1!
#310
0!
#315
0$
b0 #
1!
#320
0!
#325
1$
b1 #
1!
#330
0!
#335
0$
b0 #
1!
#340
0!
#345
1$
b1 #
1!
#350
0!
#355
0$
b0 #
1!
#360
0!
#365
1$
b1 #
1!
#370
0!
#375
0$
b0 #
1!
#380
0!
#385
1$
b1 #
1!
#390
0!
#395
0$
b0 #
1!
#400
0!
#405
1$
b1 #
1!
#410
0!
#415
0$
b0 #
1!
#420
0!
#425
1$
b1 #
1!
#430
0!
#435
0$
b0 #
1!
#440
0!
#445
1$
b1 #
1!
#450
0!
#455
0$
b0 #
1!
#460
0!
#465
1$
b1 #
1!
#470
0!
#475
0$
b0 #
1!
#480
0!
#485
1$
b1 #
1!
#490
0!
#495
0$
b0 #
1!
#500
0!
1"
#505
1!
#510
0!
0"
#515
1$
b1 #
1!
#520
0!
#525
0$
b0 #
1!
#530
0!
#535
1$
b1 #
1!
#540
0!
#545
0$
b0 #
1!
#550
0!
#555
1$
b1 #
1!
#560
0!
#565
0$
b0 #
1!
#570
0!
#575
1$
b1 #
1!
#580
0!
#585
0$
b0 #
1!
#590
0!
#595
1$
b1 #
1!
#600
0!
#605
0$
b0 #
1!
#610
0!
#615
1$
b1 #
1!
#620
0!
#625
0$
b0 #
1!
#630
0!
#635
1$
b1 #
1!
#640
0!
#645
0$
b0 #
1!
#650
0!
#655
1$
b1 #
1!
#660
0!
#665
0$
b0 #
1!
#670
0!
#675
1$
b1 #
1!
#680
0!
#685
0$
b0 #
1!
#690
0!
#695
1$
b1 #
1!
#700
0!
#705
0$
b0 #
1!
#710
0!
#715
1$
b1 #
1!
#720
0!
#725
0$
b0 #
1!
#730
0!
#735
1$
b1 #
1!
#740
0!
#745
0$
b0 #
1!
#750
0!
#755
1$
b1 #
1!
#760
0!
#765
0$
b0 #
1!
#770
0!
#775
1$
b1 #
1!
#780
0!
#785
0$
b0 #
1!
#790
0!
#795
1$
b1 #
1!
#800
0!
#805
0$
b0 #
1!
#810
0!
#815
1$
b1 #
1!
#820
0!
#825
0$
b0 #
1!
#830
0!
#835
1$
b1 #
1!
#840
0!
#845
0$
b0 #
1!
#850
0!
#855
1$
b1 #
1!
#860
0!
#865
0$
b0 #
1!
#870
0!
#875
1$
b1 #
1!
#880
0!
#885
0$
b0 #
1!
#890
0!
#895
1$
b1 #
1!
#900
0!
#905
0$
b0 #
1!
#910
0!
#915
1$
b1 #
1!
#920
0!
#925
0$
b0 #
1!
#930
0!
#935
1$
b1 #
1!
#940
0!
#945
0$
b0 #
1!
#950
0!
#955
1$
b1 #
1!
#960
0!
#965
0$
b0 #
1!
#970
0!
#975
1$
b1 #
1!
#980
0!
#985
0$
b0 #
1!
#990
0!
#995
1$
b1 #
1!
#1000
0!
#1005
0$
b0 #
1!
#1010
0!
#1015
1$
b1 #
1!
#1020
0!
#1025
0$
b0 #
1!
#1030
0!
#1035
1$
b1 #
1!
#1040
0!
#1045
0$
b0 #
1!
#1050
0!
#1055
1$
b1 #
1!
#1060
0!
#1065
0$
b0 #
1!
#1070
0!
#1075
1$
b1 #
1!
#1080
0!
#1085
0$
b0 #
1!
#1090
0!
#1095
1$
b1 #
1!
#1100
0!
#1105
0$
b0 #
1!
#1110
0!
#1115
1$
b1 #
1!
#1120
0!
#1125
0$
b0 #
1!
#1130
0!
#1135
1$
b1 #
1!
#1140
0!
#1145
0$
b0 #
1!
#1150
0!
#1155
1$
b1 #
1!
#1160
0!
#1165
0$
b0 #
1!
#1170
0!
#1175
1$
b1 #
1!
#1180
0!
#1185
0$
b0 #
1!
#1190
0!
#1195
1$
b1 #
1!
#1200
0!
#1205
0$
b0 #
1!
#1210
0!
#1215
1$
b1 #
1!
#1220
0!
#1225
0$
b0 #
1!
#1230
0!
#1235
1$
b1 #
1!
#1240
0!
#1245
0$
b0 #
1!
#1250
0!
#1255
1$
b1 #
1!
#1260
0!
#1265
0$
b0 #
1!
#1270
0!
#1275
1$
b1 #
1!
#1280
0!
#1285
0$
b0 #
1!
#1290
0!
#1295
1$
b1 #
1!
#1300
0!
#1305
0$
b0 #
1!
#1310
0!
#1315
1$
b1 #
1!
#1320
0!
#1325
0$
b0 #
1!
#1330
0!
#1335
1$
b1 #
1!
#1340
0!
#1345
0$
b0 #
1!
#1350
0!
#1355
1$
b1 #
1!
#1360
0!
#1365
0$
b0 #
1!
#1370
0!
#1375
1$
b1 #
1!
#1380
0!
#1385
0$
b0 #
1!
#1390
0!
#1395
1$
b1 #
1!
#1400
0!
#1405
0$
b0 #
1!
#1410
0!
#1415
1$
b1 #
1!
#1420
0!
#1425
0$
b0 #
1!
#1430
0!
#1435
1$
b1 #
1!
#1440
0!
#1445
0$
b0 #
1!
#1450
0!
#1455
1$
b1 #
1!
#1460
0!
#1465
0$
b0 #
1!
#1470
0!
#1475
1$
b1 #
1!
#1480
0!
#1485
0$
b0 #
1!
#1490
0!
#1495
1$
b1 #
1!
#1500
0!
#1505
0$
b0 #
1!
#1510
0!
#1515
1$
b1 #
1!
#1520
0!
#1525
0$
b0 #
1!
#1530
0!
#1535
1$
b1 #
1!
#1540
0!
#1545
0$
b0 #
1!
#1550
0!
#1555
1$
b1 #
1!
#1560
0!
#1565
0$
b0 #
1!
#1570
0!
#1575
1$
b1 #
1!
#1580
0!
#1585
0$
b0 #
1!
#1590
0!
#1595
1$
b1 #
1!
#1600
0!
#1605
0$
b0 #
1!
#1610
0!
#1615
1$
b1 #
1!
#1620
0!
#1625
0$
b0 #
1!
#1630
0!
#1635
1$
b1 #
1!
#1640
0!
#1645
0$
b0 #
1!
#1650
0!
#1655
1$
b1 #
1!
#1660
0!
#1665
0$
b0 #
1!
#1670
0!
#1675
1$
b1 #
1!
#1680
0!
#1685
0$
b0 #
1!
#1690
0!
#1695
1$
b1 #
1!
#1700
0!
#1705
0$
b0 #
1!
#1710
0!
#1715
1$
b1 #
1!
#1720
0!
#1725
0$
b0 #
1!
#1730
0!
#1735
1$
b1 #
1!
#1740
0!
#1745
0$
b0 #
1!
#1750
0!
#1755
1$
b1 #
1!
#1760
0!
#1765
0$
b0 #
1!
#1770
0!
#1775
1$
b1 #
1!
#1780
0!
#1785
0$
b0 #
1!
#1790
0!
#1795
1$
b1 #
1!
#1800
0!
#1805
0$
b0 #
1!
#1810
0!
#1815
1$
b1 #
1!
#1820
0!
#1825
0$
b0 #
1!
#1830
0!
#1835
1$
b1 #
1!
#1840
0!
#1845
0$
b0 #
1!
#1850
0!
#1855
1$
b1 #
1!
#1860
0!
#1865
0$
b0 #
1!
#1870
0!
#1875
1$
b1 #
1!
#1880
0!
#1885
0$
b0 #
1!
#1890
0!
#1895
1$
b1 #
1!
#1900
0!
#1905
0$
b0 #
1!
#1910
0!
#1915
1$
b1 #
1!
#1920
0!
#1925
0$
b0 #
1!
#1930
0!
#1935
1$
b1 #
1!
#1940
0!
#1945
0$
b0 #
1!
#1950
0!
#1955
1$
b1 #
1!
#1960
0!
#1965
0$
b0 #
1!
#1970
0!
#1975
1$
b1 #
1!
#1980
0!
#1985
0$
b0 #
1!
#1990
0!
#1995
1$
b1 #
1!
#2000
0!
#2005
0$
b0 #
1!
#2010
0!
#2015
1$
b1 #
1!
#2020
0!
#2025
0$
b0 #
1!
#2030
0!
#2035
1$
b1 #
1!
#2040
0!
#2045
0$
b0 #
1!
#2050
0!
#2055
1$
b1 #
1!
#2060
0!
#2065
0$
b0 #
1!
#2070
0!
#2075
1$
b1 #
1!
#2080
0!
#2085
0$
b0 #
1!
#2090
0!
#2095
1$
b1 #
1!
#2100
0!
#2105
0$
b0 #
1!
#2110
0!
#2115
1$
b1 #
1!
#2120
0!
#2125
0$
b0 #
1!
#2130
0!
#2135
1$
b1 #
1!
#2140
0!
#2145
0$
b0 #
1!
#2150
0!
#2155
1$
b1 #
1!
#2160
0!
#2165
0$
b0 #
1!
#2170
0!
#2175
1$
b1 #
1!
#2180
0!
#2185
0$
b0 #
1!
#2190
0!
#2195
1$
b1 #
1!
#2200
0!
#2205
0$
b0 #
1!
#2210
0!
#2215
1$
b1 #
1!
#2220
0!
#2225
0$
b0 #
1!
#2230
0!
#2235
1$
b1 #
1!
#2240
0!
#2245
0$
b0 #
1!
#2250
0!
#2255
1$
b1 #
1!
#2260
0!
#2265
0$
b0 #
1!
#2270
0!
#2275
1$
b1 #
1!
#2280
0!
#2285
0$
b0 #
1!
#2290
0!
#2295
1$
b1 #
1!
#2300
0!
#2305
0$
b0 #
1!
#2310
0!
#2315
1$
b1 #
1!
#2320
0!
#2325
0$
b0 #
1!
#2330
0!
#2335
1$
b1 #
1!
#2340
0!
#2345
0$
b0 #
1!
#2350
0!
#2355
1$
b1 #
1!
#2360
0!
#2365
0$
b0 #
1!
#2370
0!
#2375
1$
b1 #
1!
#2380
0!
#2385
0$
b0 #
1!
#2390
0!
#2395
1$
b1 #
1!
#2400
0!
#2405
0$
b0 #
1!
#2410
0!
#2415
1$
b1 #
1!
#2420
0!
#2425
0$
b0 #
1!
#2430
0!
#2435
1$
b1 #
1!
#2440
0!
#2445
0$
b0 #
1!
#2450
0!
#2455
1$
b1 #
1!
#2460
0!
#2465
0$
b0 #
1!
#2470
0!
#2475
1$
b1 #
1!
#2480
0!
#2485
0$
b0 #
1!
#2490
0!
#2495
1$
b1 #
1!
#2500
0!
#2505
0$
b0 #
1!
#2510
0!
#2515
1$
b1 #
1!
#2520
0!
#2525
0$
b0 #
1!
#2530
0!
#2535
1$
b1 #
1!
#2540
0!
#2545
0$
b0 #
1!
#2550
0!
#2555
1$
b1 #
1!
#2560
0!
#2565
0$
b0 #
1!
#2570
0!
#2575
1$
b1 #
1!
#2580
0!
#2585
0$
b0 #
1!
#2590
0!
#2595
1$
b1 #
1!
#2600
0!
#2605
0$
b0 #
1!
#2610
0!
#2615
1$
b1 #
1!
#2620
0!
#2625
0$
b0 #
1!
#2630
0!
#2635
1$
b1 #
1!
#2640
0!
#2645
0$
b0 #
1!
#2650
0!
#2655
1$
b1 #
1!
#2660
0!
#2665
0$
b0 #
1!
#2670
0!
#2675
1$
b1 #
1!
#2680
0!
#2685
0$
b0 #
1!
#2690
0!
#2695
1$
b1 #
1!
#2700
0!
#2705
0$
b0 #
1!
#2710
0!
#2715
1$
b1 #
1!
#2720
0!
#2725
0$
b0 #
1!
#2730
0!
#2735
1$
b1 #
1!
#2740
0!
#2745
0$
b0 #
1!
#2750
0!
#2755
1$
b1 #
1!
#2760
0!
#2765
0$
b0 #
1!
#2770
0!
#2775
1$
b1 #
1!
#2780
0!
#2785
0$
b0 #
1!
#2790
0!
#2795
1$
b1 #
1!
#2800
0!
#2805
0$
b0 #
1!
#2810
0!
#2815
1$
b1 #
1!
#2820
0!
#2825
0$
b0 #
1!
#2830
0!
#2835
1$
b1 #
1!
#2840
0!
#2845
0$
b0 #
1!
#2850
0!
#2855
1$
b1 #
1!
#2860
0!
#2865
0$
b0 #
1!
#2870
0!
#2875
1$
b1 #
1!
#2880
0!
#2885
0$
b0 #
1!
#2890
0!
#2895
1$
b1 #
1!
#2900
0!
#2905
0$
b0 #
1!
#2910
0!
#2915
1$
b1 #
1!
#2920
0!
#2925
0$
b0 #
1!
#2930
0!
#2935
1$
b1 #
1!
#2940
0!
#2945
0$
b0 #
1!
#2950
0!
#2955
1$
b1 #
1!
#2960
0!
#2965
0$
b0 #
1!
#2970
0!
#2975
1$
b1 #
1!
#2980
0!
#2985
0$
b0 #
1!
#2990
0!
#2995
1$
b1 #
1!
#3000
0!
#3005
0$
b0 #
1!
#3010
0!
#3015
1$
b1 #
1!
#3020
0!
#3025
0$
b0 #
1!
#3030
0!
#3035
1$
b1 #
1!
#3040
0!
#3045
0$
b0 #
1!
#3050
0!
#3055
1$
b1 #
1!
#3060
0!
#3065
0$
b0 #
1!
#3070
0!
#3075
1$
b1 #
1!
#3080
0!
#3085
0$
b0 #
1!
#3090
0!
#3095
1$
b1 #
1!
#3100
0!
#3105
0$
b0 #
1!
#3110
0!
#3115
1$
b1 #
1!
#3120
0!
#3125
0$
b0 #
1!
#3130
0!
#3135
1$
b1 #
1!
#3140
0!
#3145
0$
b0 #
1!
#3150
0!
#3155
1$
b1 #
1!
#3160
0!
#3165
0$
b0 #
1!
#3170
0!
#3175
1$
b1 #
1!
#3180
0!
#3185
0$
b0 #
1!
#3190
0!
#3195
1$
b1 #
1!
#3200
0!
#3205
0$
b0 #
1!
#3210
0!
#3215
1$
b1 #
1!
#3220
0!
#3225
0$
b0 #
1!
#3230
0!
#3235
1$
b1 #
1!
#3240
0!
#3245
0$
b0 #
1!
#3250
0!
#3255
1$
b1 #
1!
#3260
0!
#3265
0$
b0 #
1!
#3270
0!
#3275
1$
b1 #
1!
#3280
0!
#3285
0$
b0 #
1!
#3290
0!
#3295
1$
b1 #
1!
#3300
0!
#3305
0$
b0 #
1!
#3310
0!
#3315
1$
b1 #
1!
#3320
0!
#3325
0$
b0 #
1!
#3330
0!
#3335
1$
b1 #
1!
#3340
0!
#3345
0$
b0 #
1!
#3350
0!
#3355
1$
b1 #
1!
#3360
0!
#3365
0$
b0 #
1!
#3370
0!
#3375
1$
b1 #
1!
#3380
0!
#3385
0$
b0 #
1!
#3390
0!
#3395
1$
b1 #
1!
#3400
0!
#3405
0$
b0 #
1!
#3410
0!
#3415
1$
b1 #
1!
#3420
0!
#3425
0$
b0 #
1!
#3430
0!
#3435
1$
b1 #
1!
#3440
0!
#3445
0$
b0 #
1!
#3450
0!
#3455
1$
b1 #
1!
#3460
0!
#3465
0$
b0 #
1!
#3470
0!
#3475
1$
b1 #
1!
#3480
0!
#3485
0$
b0 #
1!
#3490
0!
#3495
1$
b1 #
1!
#3500
0!
#3505
0$
b0 #
1!
#3510
0!
#3515
1$
b1 #
1!
#3520
0!
#3525
0$
b0 #
1!
#3530
0!
#3535
1$
b1 #
1!
#3540
0!
#3545
0$
b0 #
1!
#3550
0!
#3555
1$
b1 #
1!
#3560
0!
#3565
0$
b0 #
1!
#3570
0!
#3575
1$
b1 #
1!
#3580
0!
#3585
0$
b0 #
1!
#3590
0!
#3595
1$
b1 #
1!
#3600
0!
#3605
0$
b0 #
1!
#3610
0!
#3615
1$
b1 #
1!
#3620
0!
#3625
0$
b0 #
1!
#3630
0!
#3635
1$
b1 #
1!
#3640
0!
#3645
0$
b0 #
1!
#3650
0!
#3655
1$
b1 #
1!
#3660
0!
#3665
0$
b0 #
1!
#3670
0!
#3675
1$
b1 #
1!
#3680
0!
#3685
0$
b0 #
1!
#3690
0!
#3695
1$
b1 #
1!
#3700
0!
#3705
0$
b0 #
1!
#3710
0!
#3715
1$
b1 #
1!
#3720
0!
#3725
0$
b0 #
1!
#3730
0!
#3735
1$
b1 #
1!
#3740
0!
#3745
0$
b0 #
1!
#3750
0!
#3755
1$
b1 #
1!
#3760
0!
#3765
0$
b0 #
1!
#3770
0!
#3775
1$
b1 #
1!
#3780
0!
#3785
0$
b0 #
1!
#3790
0!
#3795
1$
b1 #
1!
#3800
0!
#3805
0$
b0 #
1!
#3810
0!
#3815
1$
b1 #
1!
#3820
0!
#3825
0$
b0 #
1!
#3830
0!
#3835
1$
b1 #
1!
#3840
0!
#3845
0$
b0 #
1!
#3850
0!
#3855
1$
b1 #
1!
#3860
0!
#3865
0$
b0 #
1!
#3870
0!
#3875
1$
b1 #
1!
#3880
0!
#3885
0$
b0 #
1!
#3890
0!
#3895
1$
b1 #
1!
#3900
0!
#3905
0$
b0 #
1!
#3910
0!
#3915
1$
b1 #
1!
#3920
0!
#3925
0$
b0 #
1!
#3930
0!
#3935
1$
b1 #
1!
#3940
0!
#3945
0$
b0 #
1!
#3950
0!
#3955
1$
b1 #
1!
#3960
0!
#3965
0$
b0 #
1!
#3970
0!
#3975
1$
b1 #
1!
#3980
0!
#3985
0$
b0 #
1!
#3990
0!
#3995
1$
b1 #
1!
#4000
0!
#4005
0$
b0 #
1!
#4010
0!
#4015
1$
b1 #
1!
#4020
0!
#4025
0$
b0 #
1!
#4030
0!
#4035
1$
b1 #
1!
#4040
0!
#4045
0$
b0 #
1!
#4050
0!
#4055
1$
b1 #
1!
#4060
0!
#4065
0$
b0 #
1!
#4070
0!
#4075
1$
b1 #
1!
#4080
0!
#4085
0$
b0 #
1!
#4090
0!
#4095
1$
b1 #
1!
#4100
0!
#4105
0$
b0 #
1!
#4110
0!
#4115
1$
b1 #
1!
#4120
0!
#4125
0$
b0 #
1!
#4130
0!
#4135
1$
b1 #
1!
#4140
0!
#4145
0$
b0 #
1!
#4150
0!
#4155
1$
b1 #
1!
#4160
0!
#4165
0$
b0 #
1!
#4170
0!
#4175
1$
b1 #
1!
#4180
0!
#4185
0$
b0 #
1!
#4190
0!
#4195
1$
b1 #
1!
#4200
0!
#4205
0$
b0 #
1!
#4210
0!
#4215
1$
b1 #
1!
#4220
0!
#4225
0$
b0 #
1!
#4230
0!
#4235
1$
b1 #
1!
#4240
0!
#4245
0$
b0 #
1!
#4250
0!
#4255
1$
b1 #
1!
#4260
0!
#4265
0$
b0 #
1!
#4270
0!
#4275
1$
b1 #
1!
#4280
0!
#4285
0$
b0 #
1!
#4290
0!
#4295
1$
b1 #
1!
#4300
0!
#4305
0$
b0 #
1!
#4310
0!
#4315
1$
b1 #
1!
#4320
0!
#4325
0$
b0 #
1!
#4330
0!
#4335
1$
b1 #
1!
#4340
0!
#4345
0$
b0 #
1!
#4350
0!
#4355
1$
b1 #
1!
#4360
0!
#4365
0$
b0 #
1!
#4370
0!
#4375
1$
b1 #
1!
#4380
0!
#4385
0$
b0 #
1!
#4390
0!
#4395
1$
b1 #
1!
#4400
0!
#4405
0$
b0 #
1!
#4410
0!
#4415
1$
b1 #
1!
#4420
0!
#4425
0$
b0 #
1!
#4430
0!
#4435
1$
b1 #
1!
#4440
0!
#4445
0$
b0 #
1!
#4450
0!
#4455
1$
b1 #
1!
#4460
0!
#4465
0$
b0 #
1!
#4470
0!
#4475
1$
b1 #
1!
#4480
0!
#4485
0$
b0 #
1!
#4490
0!
#4495
1$
b1 #
1!
#4500
0!
#4505
0$
b0 #
1!
#4510
0!
#4515
1$
b1 #
1!
#4520
0!
#4525
0$
b0 #
1!
#4530
0!
#4535
1$
b1 #
1!
#4540
0!
#4545
0$
b0 #
1!
#4550
0!
#4555
1$
b1 #
1!
#4560
0!
#4565
0$
b0 #
1!
#4570
0!
#4575
1$
b1 #
1!
#4580
0!
#4585
0$
b0 #
1!
#4590
0!
#4595
1$
b1 #
1!
#4600
0!
#4605
0$
b0 #
1!
#4610
0!
#4615
1$
b1 #
1!
#4620
0!
#4625
0$
b0 #
1!
#4630
0!
#4635
1$
b1 #
1!
#4640
0!
#4645
0$
b0 #
1!
#4650
0!
#4655
1$
b1 #
1!
#4660
0!
#4665
0$
b0 #
1!
#4670
0!
#4675
1$
b1 #
1!
#4680
0!
#4685
0$
b0 #
1!
#4690
0!
#4695
1$
b1 #
1!
#4700
0!
#4705
0$
b0 #
1!
#4710
0!
#4715
1$
b1 #
1!
#4720
0!
#4725
0$
b0 #
1!
#4730
0!
#4735
1$
b1 #
1!
#4740
0!
#4745
0$
b0 #
1!
#4750
0!
#4755
1$
b1 #
1!
#4760
0!
#4765
0$
b0 #
1!
#4770
0!
#4775
1$
b1 #
1!
#4780
0!
#4785
0$
b0 #
1!
#4790
0!
#4795
1$
b1 #
1!
#4800
0!
#4805
0$
b0 #
1!
#4810
0!
#4815
1$
b1 #
1!
#4820
0!
#4825
0$
b0 #
1!
#4830
0!
#4835
1$
b1 #
1!
#4840
0!
#4845
0$
b0 #
1!
#4850
0!
#4855
1$
b1 #
1!
#4860
0!
#4865
0$
b0 #
1!
#4870
0!
#4875
1$
b1 #
1!
#4880
0!
#4885
0$
b0 #
1!
#4890
0!
#4895
1$
b1 #
1!
#4900
0!
#4905
0$
b0 #
1!
#4910
0!
#4915
1$
b1 #
1!
#4920
0!
#4925
0$
b0 #
1!
#4930
0!
#4935
1$
b1 #
1!
#4940
0!
#4945
0$
b0 #
1!
#4950
0!
#4955
1$
b1 #
1!
#4960
0!
#4965
0$
b0 #
1!
#4970
0!
#4975
1$
b1 #
1!
#4980
0!
#4985
0$
b0 #
1!
#4990
0!
#4995
1$
b1 #
1!
#5000
0!
#5005
0$
b0 #
1!
#5010
0!
#5015
1$
b1 #
1!
#5020
0!
#5025
0$
b0 #
1!
#5030
0!
#5035
1$
b1 #
1!
#5040
0!
#5045
0$
b0 #
1!
#5050
0!
#5055
1$
b1 #
1!
#5060
0!
#5065
0$
b0 #
1!
#5070
0!
#5075
1$
b1 #
1!
#5080
0!
#5085
0$
b0 #
1!
#5090
0!
#5095
1$
b1 #
1!
#5100
0!
#5105
0$
b0 #
1!
#5110
0!
#5115
1$
b1 #
1!
#5120
0!
#5125
0$
b0 #
1!
#5130
0!
#5135
1$
b1 #
1!
#5140
0!
#5145
0$
b0 #
1!
#5150
0!
#5155
1$
b1 #
1!
#5160
0!
#5165
0$
b0 #
1!
#5170
0!
#5175
1$
b1 #
1!
#5180
0!
#5185
0$
b0 #
1!
#5190
0!
#5195
1$
b1 #
1!
#5200
0!
#5205
0$
b0 #
1!
#5210
0!
#5215
1$
b1 #
1!
#5220
0!
#5225
0$
b0 #
1!
#5230
0!
#5235
1$
b1 #
1!
#5240
0!
#5245
0$
b0 #
1!
#5250
0!
#5255
1$
b1 #
1!
#5260
0!
#5265
0$
b0 #
1!
#5270
0!
#5275
1$
b1 #
1!
#5280
0!
#5285
0$
b0 #
1!
#5290
0!
#5295
1$
b1 #
1!
#5300
0!
#5305
0$
b0 #
1!
#5310
0!
#5315
1$
b1 #
1!
#5320
0!
#5325
0$
b0 #
1!
#5330
0!
#5335
1$
b1 #
1!
#5340
0!
#5345
0$
b0 #
1!
#5350
0!
#5355
1$
b1 #
1!
#5360
0!
#5365
0$
b0 #
1!
#5370
0!
#5375
1$
b1 #
1!
#5380
0!
#5385
0$
b0 #
1!
#5390
0!
#5395
1$
b1 #
1!
#5400
0!
#5405
0$
b0 #
1!
#5410
0!
#5415
1$
b1 #
1!
#5420
0!
#5425
0$
b0 #
1!
#5430
0!
#5435
1$
b1 #
1!
#5440
0!
#5445
0$
b0 #
1!
#5450
0!
#5455
1$
b1 #
1!
#5460
0!
#5465
0$
b0 #
1!
#5470
0!
#5475
1$
b1 #
1!
#5480
0!
#5485
0$
b0 #
1!
#5490
0!
#5495
1$
b1 #
1!
#5500
0!
#5505
0$
b0 #
1!
#5510
0!
#5515
1$
b1 #
1!
#5520
0!
#5525
0$
b0 #
1!
#5530
0!
#5535
1$
b1 #
1!
#5540
0!
#5545
0$
b0 #
1!
#5550
0!
#5555
1$
b1 #
1!
#5560
0!
#5565
0$
b0 #
1!
#5570
0!
#5575
1$
b1 #
1!
#5580
0!
#5585
0$
b0 #
1!
#5590
0!
#5595
1$
b1 #
1!
#5600
0!
#5605
0$
b0 #
1!
#5610
0!
#5615
1$
b1 #
1!
#5620
0!
#5625
0$
b0 #
1!
#5630
0!
#5635
1$
b1 #
1!
#5640
0!
#5645
0$
b0 #
1!
#5650
0!
#5655
1$
b1 #
1!
#5660
0!
#5665
0$
b0 #
1!
#5670
0!
#5675
1$
b1 #
1!
#5680
0!
#5685
0$
b0 #
1!
#5690
0!
#5695
1$
b1 #
1!
#5700
0!
#5705
0$
b0 #
1!
#5710
0!
#5715
1$
b1 #
1!
#5720
0!
#5725
0$
b0 #
1!
#5730
0!
#5735
1$
b1 #
1!
#5740
0!
#5745
0$
b0 #
1!
#5750
0!
#5755
1$
b1 #
1!
#5760
0!
#5765
0$
b0 #
1!
#5770
0!
#5775
1$
b1 #
1!
#5780
0!
#5785
0$
b0 #
1!
#5790
0!
#5795
1$
b1 #
1!
#5800
0!
#5805
0$
b0 #
1!
#5810
0!
#5815
1$
b1 #
1!
#5820
0!
#5825
0$
b0 #
1!
#5830
0!
#5835
1$
b1 #
1!
#5840
0!
#5845
0$
b0 #
1!
#5850
0!
#5855
1$
b1 #
1!
#5860
0!
#5865
0$
b0 #
1!
#5870
0!
#5875
1$
b1 #
1!
#5880
0!
#5885
0$
b0 #
1!
#5890
0!
#5895
1$
b1 #
1!
#5900
0!
#5905
0$
b0 #
1!
#5910
0!
#5915
1$
b1 #
1!
#5920
0!
#5925
0$
b0 #
1!
#5930
0!
#5935
1$
b1 #
1!
#5940
0!
#5945
0$
b0 #
1!
#5950
0!
#5955
1$
b1 #
1!
#5960
0!
#5965
0$
b0 #
1!
#5970
0!
#5975
1$
b1 #
1!
#5980
0!
#5985
0$
b0 #
1!
#5990
0!
#5995
1$
b1 #
1!
#6000
0!
#6005
0$
b0 #
1!
#6010
0!
#6015
1$
b1 #
1!
#6020
0!
#6025
0$
b0 #
1!
#6030
0!
#6035
1$
b1 #
1!
#6040
0!
#6045
0$
b0 #
1!
#6050
0!
#6055
1$
b1 #
1!
#6060
0!
#6065
0$
b0 #
1!
#6070
0!
#6075
1$
b1 #
1!
#6080
0!
#6085
0$
b0 #
1!
#6090
0!
#6095
1$
b1 #
1!
#6100
0!
#6105
0$
b0 #
1!
#6110
0!
#6115
1$
b1 #
1!
#6120
0!
#6125
0$
b0 #
1!
#6130
0!
#6135
1$
b1 #
1!
#6140
0!
#6145
0$
b0 #
1!
#6150
0!
#6155
1$
b1 #
1!
#6160
0!
#6165
0$
b0 #
1!
#6170
0!
#6175
1$
b1 #
1!
#6180
0!
#6185
0$
b0 #
1!
#6190
0!
#6195
1$
b1 #
1!
#6200
0!
#6205
0$
b0 #
1!
#6210
0!
#6215
1$
b1 #
1!
#6220
0!
#6225
0$
b0 #
1!
#6230
0!
#6235
1$
b1 #
1!
#6240
0!
#6245
0$
b0 #
1!
#6250
0!
#6255
1$
b1 #
1!
#6260
0!
#6265
0$
b0 #
1!
#6270
0!
#6275
1$
b1 #
1!
#6280
0!
#6285
0$
b0 #
1!
#6290
0!
#6295
1$
b1 #
1!
#6300
0!
#6305
0$
b0 #
1!
#6310
0!
#6315
1$
b1 #
1!
#6320
0!
#6325
0$
b0 #
1!
#6330
0!
#6335
1$
b1 #
1!
#6340
0!
#6345
0$
b0 #
1!
#6350
0!
#6355
1$
b1 #
1!
#6360
0!
#6365
0$
b0 #
1!
#6370
0!
#6375
1$
b1 #
1!
#6380
0!
#6385
0$
b0 #
1!
#6390
0!
#6395
1$
b1 #
1!
#6400
0!
#6405
0$
b0 #
1!
#6410
0!
#6415
1$
b1 #
1!
#6420
0!
#6425
0$
b0 #
1!
#6430
0!
#6435
1$
b1 #
1!
#6440
0!
#6445
0$
b0 #
1!
#6450
0!
#6455
1$
b1 #
1!
#6460
0!
#6465
0$
b0 #
1!
#6470
0!
#6475
1$
b1 #
1!
#6480
0!
#6485
0$
b0 #
1!
#6490
0!
#6495
1$
b1 #
1!
#6500
0!
#6505
0$
b0 #
1!
#6510
0!
#6515
1$
b1 #
1!
#6520
0!
#6525
0$
b0 #
1!
#6530
0!
#6535
1$
b1 #
1!
#6540
0!
#6545
0$
b0 #
1!
#6550
0!
